spaps_client/__init__.py
spaps_client/async_client.py
spaps_client/auth.py
spaps_client/auth_async.py
spaps_client/client.py
spaps_client/config.py
spaps_client/crypto.py
spaps_client/crypto_async.py
spaps_client/entitlements.py
spaps_client/entitlements_async.py
spaps_client/http.py
spaps_client/http_async.py
spaps_client/metrics.py
spaps_client/metrics_async.py
spaps_client/payments.py
spaps_client/payments_async.py
spaps_client/permissions.py
spaps_client/py.typed
spaps_client/secure_messages.py
spaps_client/secure_messages_async.py
spaps_client/sessions.py
spaps_client/sessions_async.py
spaps_client/storage.py
spaps_client/usage.py
spaps_client/usage_async.py
spaps_client/webhooks.py
spaps_client/whitelist.py
spaps_client/whitelist_async.py
spaps-0.2.0.dist-info/METADATA
spaps-0.2.0.dist-info/WHEEL
spaps-0.2.0.dist-info/licenses/LICENSE
spaps-0.2.0.dist-info/RECORD
