Metadata-Version: 2.4
Name: spaps
Version: 0.2.0
Summary: Sweet Potato Authentication & Payment Service Python client
Project-URL: Homepage, https://api.sweetpotato.dev
Project-URL: Repository, https://github.com/sweet-potato/spaps
Author-email: buildooor <buildooor@gmail.com>
License: MIT License
License-File: LICENSE
Keywords: authentication,payments,spaps,sweet-potato
Classifier: Intended Audience :: Developers
Classifier: License :: OSI Approved :: MIT License
Classifier: Programming Language :: Python :: 3
Classifier: Programming Language :: Python :: 3 :: Only
Classifier: Programming Language :: Python :: 3.9
Classifier: Programming Language :: Python :: 3.10
Classifier: Programming Language :: Python :: 3.11
Classifier: Programming Language :: Python :: 3.12
Classifier: Topic :: Software Development :: Libraries :: Application Frameworks
Requires-Python: >=3.9
Requires-Dist: httpx<0.29.0,>=0.27.0
Requires-Dist: pydantic<3.0.0,>=2.7.0
Provides-Extra: dev
Requires-Dist: build<2.0.0,>=1.2.1; extra == 'dev'
Requires-Dist: httpx<0.29.0,>=0.27.0; extra == 'dev'
Requires-Dist: mypy<2.0.0,>=1.10.0; extra == 'dev'
Requires-Dist: pydantic<3.0.0,>=2.7.0; extra == 'dev'
Requires-Dist: pytest-asyncio>=0.23.0; extra == 'dev'
Requires-Dist: pytest-cov>=5.0.0; extra == 'dev'
Requires-Dist: pytest>=8.0.0; extra == 'dev'
Requires-Dist: respx<0.23.0,>=0.22.0; extra == 'dev'
Requires-Dist: ruff<1.0.0,>=0.5.5; extra == 'dev'
Requires-Dist: tomli<3.0.0,>=2.0.1; extra == 'dev'
